ons_metadata_validation/__init__.py
ons_metadata_validation/__main__.py
ons_metadata_validation/extraction/extract_metadata.py
ons_metadata_validation/extraction/metadata_utils.py
ons_metadata_validation/fixing/__init__.py
ons_metadata_validation/fixing/fixing_utils.py
ons_metadata_validation/fixing/string_fixes.py
ons_metadata_validation/ids_common_utils/build_spark_schema.py
ons_metadata_validation/ids_common_utils/cleaning.py
ons_metadata_validation/ids_common_utils/metadata_key.py
ons_metadata_validation/ids_common_utils/nested_columns.py
ons_metadata_validation/ids_common_utils/spark_datatype.py
ons_metadata_validation/outputs/__init__.py
ons_metadata_validation/outputs/excel_outputs.py
ons_metadata_validation/outputs/field_constants.py
ons_metadata_validation/outputs/manifests.py
ons_metadata_validation/outputs/output_constants.py
ons_metadata_validation/processing/__init__.py
ons_metadata_validation/processing/convert_json_to_v2_template.py
ons_metadata_validation/processing/convert_to_version.py
ons_metadata_validation/processing/data_structures.py
ons_metadata_validation/processing/processor.py
ons_metadata_validation/processing/utils.py
ons_metadata_validation/processing/validate_funcs.py
ons_metadata_validation/reference/__init__.py
ons_metadata_validation/reference/constants.py
ons_metadata_validation/reference/delta_table.py
ons_metadata_validation/reference/lookups.py
ons_metadata_validation/reference/role_configs.py
ons_metadata_validation/reference/template.py
ons_metadata_validation/utils/__init__.py
ons_metadata_validation/utils/logger.py
ons_metadata_validation/validation/__init__.py
ons_metadata_validation/validation/_comparative_validation_checks.py
ons_metadata_validation/validation/_rowwise_validation_checks.py
ons_metadata_validation/validation/_validation_checks.py
ons_metadata_validation/validation/_validation_utils.py
ons_metadata_validation/validation/comparative_validations.py
ons_metadata_validation/validation/rowwise_validations.py
ons_metadata_validation-1.2.8.dist-info/METADATA
ons_metadata_validation-1.2.8.dist-info/WHEEL
ons_metadata_validation-1.2.8.dist-info/top_level.txt
ons_metadata_validation-1.2.8.dist-info/RECORD
