Metadata-Version: 2.4
Name: ons-metadata-validation
Version: 1.2.8
Summary: automated metadata validation for ONS metadata templates
Author: ONS Data Engineers
Project-URL: homepage, https://github.com/ONSdigital/automated-metadata-validation
Requires-Python: >=3.10
Requires-Dist: attrs>=22.2.0
Requires-Dist: numpy>=1.19.5
Requires-Dist: openpyxl>=3.1.2
Requires-Dist: pandas>=1.5
Requires-Dist: pyspark==3.5.6
Requires-Dist: tqdm>=4.64.0
Provides-Extra: out-of-dap
Requires-Dist: pyspark<3.7,>3; extra == "out-of-dap"
Provides-Extra: test
Requires-Dist: pytest; extra == "test"
Requires-Dist: pytest-cov; extra == "test"
Provides-Extra: lint
Requires-Dist: pre-commit; extra == "lint"
Requires-Dist: ruff==0.4.2; extra == "lint"
Provides-Extra: dev
Requires-Dist: bump2version==1.0.1; extra == "dev"
Requires-Dist: ons-metadata-validation[lint,test]; extra == "dev"
